api/__init__.py
api/holobit_pb2.py
api/holobit_pb2_grpc.py
holobit_sdk/__init__.py
holobit_sdk/api/__init__.py
holobit_sdk/api/grpc_service.py
holobit_sdk/api/python_bridge.py
holobit_sdk/api/service.py
holobit_sdk/api/tests/__init__.py
holobit_sdk/api/tests/test_python_bridge.py
holobit_sdk/api/tests/test_service_limits.py
holobit_sdk/asiic_holographic/__init__.py
holobit_sdk/asiic_holographic/instructions.py
holobit_sdk/asiic_holographic/interpreter.py
holobit_sdk/asiic_holographic/translator.py
holobit_sdk/asiic_holographic/tests/__init__.py
holobit_sdk/asiic_holographic/tests/test_asiic.py
holobit_sdk/assembler/__init__.py
holobit_sdk/assembler/executor.py
holobit_sdk/assembler/macros.py
holobit_sdk/assembler/parser.py
holobit_sdk/assembler/virtual_machine.py
holobit_sdk/cloud/__init__.py
holobit_sdk/cloud/aws.py
holobit_sdk/cloud/azure.py
holobit_sdk/cloud/base.py
holobit_sdk/cloud/credentials.py
holobit_sdk/cloud/gcp.py
holobit_sdk/cloud/universal.py
holobit_sdk/core/__init__.py
holobit_sdk/core/genetic_optimizer.py
holobit_sdk/core/holobit.py
holobit_sdk/core/interactions.py
holobit_sdk/core/operations.py
holobit_sdk/core/quark.py
holobit_sdk/multi_level/__init__.py
holobit_sdk/multi_level/high_level/__init__.py
holobit_sdk/multi_level/high_level/c_backend.py
holobit_sdk/multi_level/high_level/compiler.py
holobit_sdk/multi_level/high_level/debugger.py
holobit_sdk/multi_level/high_level/go_backend.py
holobit_sdk/multi_level/high_level/hololang_cli.py
holobit_sdk/multi_level/high_level/hololang_parser.py
holobit_sdk/multi_level/high_level/rust_backend.py
holobit_sdk/multi_level/high_level/tests/__init__.py
holobit_sdk/multi_level/high_level/tests/test_c_backend.py
holobit_sdk/multi_level/high_level/tests/test_compiler.py
holobit_sdk/multi_level/high_level/tests/test_complex_variables.py
holobit_sdk/multi_level/high_level/tests/test_constants_comments.py
holobit_sdk/multi_level/high_level/tests/test_fractal_hololang.py
holobit_sdk-1.0.9.dist-info/licenses/LICENSE
holobit_sdk-1.0.9.dist-info/METADATA
holobit_sdk-1.0.9.dist-info/WHEEL
holobit_sdk-1.0.9.dist-info/entry_points.txt
holobit_sdk-1.0.9.dist-info/top_level.txt
holobit_sdk-1.0.9.dist-info/RECORD
