Metadata-Version: 2.4
Name: holobit-sdk
Version: 1.0.9
Summary: SDK para arquitectura holográfica avanzada
Home-page: https://github.com/Alphonsus411/holobit_SDK
Author: Adolfo González Hernández
Author-email: Adolfo González Hernández <adolfogonzal@gmail.com>
License: MIT
Requires-Python: >=3.10
License-File: LICENSE
Requires-Dist: numpy
Requires-Dist: matplotlib
Provides-Extra: qiskit
Requires-Dist: qiskit; extra == "qiskit"
Provides-Extra: pennylane
Requires-Dist: pennylane; extra == "pennylane"
Provides-Extra: aws
Requires-Dist: boto3; extra == "aws"
Provides-Extra: azure
Requires-Dist: azure-identity; extra == "azure"
Provides-Extra: gcp
Requires-Dist: google-cloud-compute; extra == "gcp"
Dynamic: author
Dynamic: home-page
Dynamic: license-file
Dynamic: requires-python
